lpsd/__init__.py
lpsd/_helpers.py
lpsd/_lcsd.py
lpsd/flattop.py
lpsd/ltpda_dft.dll
lpsd/ltpda_dft.so
lpsd/wrapper.py
lpsd-1.0.6.dist-info/LICENSE
lpsd-1.0.6.dist-info/METADATA
lpsd-1.0.6.dist-info/WHEEL
lpsd-1.0.6.dist-info/RECORD
