Metadata-Version: 2.1
Name: lpsd
Version: 1.0.6
Summary: Python and C implementation for logarithmical power spectral density (LPSD) calculation.
Home-page: https://gitlab.com/uhh-gwd/lpsd
Author: Christoph Bode
Author-email: christoph.bode@aei.mpg.de
Maintainer: Christian Darsow-Fromm
Maintainer-email: cdarsowf@physnet.uni-hamburg.de
Requires-Python: >=3.10,<3.16
Classifier: Programming Language :: Python :: 3
Classifier: Programming Language :: Python :: 3.10
Classifier: Programming Language :: Python :: 3.11
Requires-Dist: importlib-metadata (>=1.1.3,<2.0.0) ; python_full_version <= "3.7.0"
Requires-Dist: numpy (>=1.18,<3.0)
Requires-Dist: pandas (>=1.0,<3.0)
Requires-Dist: scipy (>=1.5,<2.0)
Project-URL: Documentation, https://gitlab.com/uhh-gwd/lpsd/-/blob/main/README.md
Project-URL: Repository, https://gitlab.com/uhh-gwd/lpsd
